magma_ven/__init__.py
magma_ven/const.py
magma_ven/download.py
magma_ven/magma_ven.py
magma_ven/utils.py
magma_ven-0.0.3.dist-info/licenses/LICENSE
magma_ven-0.0.3.dist-info/WHEEL
magma_ven-0.0.3.dist-info/METADATA
magma_ven-0.0.3.dist-info/RECORD
