Metadata-Version: 2.4
Name: magma-ven
Version: 0.0.3
Summary: MAGMA Volcano Eruption Notice (VEN)
Keywords: magma,indonesia,volcano,eruption,magma indonesia,volcanoes
Author-email: Martanto <martanto@live.com>, Devy Kamil Syahbana <devy.syahbana@gmail.com>, Syarif Abdul Manaf <riefmof@gmail.com>
Requires-Python: >=3.11
Classifier: License :: OSI Approved :: MIT License
Classifier: Operating System :: OS Independent
Classifier: Programming Language :: Python :: 3.11
Classifier: Programming Language :: Python :: 3.12
License-File: LICENSE
Requires-Dist: openpyxl>=3.1.5
Requires-Dist: pandas>=2.2.2
Requires-Dist: numpy>=2.2.5
Requires-Dist: matplotlib>=3.9.0
Requires-Dist: magma-database>=1.5.0
Requires-Dist: magma-auth
Requires-Dist: black[d] ; extra == "dev"
Requires-Dist: isort ; extra == "dev"
Requires-Dist: openpyxl ; extra == "dev"
Requires-Dist: pandas ; extra == "dev"
Requires-Dist: numpy ; extra == "dev"
Requires-Dist: matplotlib ; extra == "dev"
Requires-Dist: magma-database ; extra == "dev"
Requires-Dist: magma-auth ; extra == "dev"
Project-URL: Homepage, https://github.com/martanto/magma-ven
Project-URL: Issues, https://github.com/martanto/magma-ven/issues
Provides-Extra: dev
